{
    "IndelModels": {
        "Binom": {
            "Date": "07/21/2015",
            "MaxMotifLength": 2,
            "MaxTractLength": 34,
            "Model": [
                [
                    [
                        5.1678184876047375e-05,
                        5.7974499470913235e-05
                    ],
                    [
                        5.1678184876047375e-05,
                        5.7974499470913235e-05
                    ],
                    [
                        5.1678184876047375e-05,
                        5.7974499470913235e-05
                    ],
                    [
                        5.1678184876047375e-05,
                        5.7974499470913235e-05
                    ],
                    [
                        5.1678184876047375e-05,
                        5.7974499470913235e-05
                    ],
                    [
                        5.1678184876047375e-05,
                        5.7974499470913235e-05
                    ],
                    [
                        5.1678184876047375e-05,
                        5.7974499470913235e-05
                    ],
                    [
                        5.1678184876047375e-05,
                        5.7974499470913235e-05
                    ],
                    [
                        6.34380219641412e-05,
                        7.419089588828067e-05
                    ],
                    [
                        0.0001272737552614706,
                        0.00011135823963739687
                    ],
                    [
                        0.00019608403800415808,
                        0.00015267299955513513
                    ],
                    [
                        0.00022231503571254157,
                        0.00019014117116023305
                    ],
                    [
                        0.00023656734579116862,
                        0.00022235861706141808
                    ],
                    [
                        0.00024818778671693907,
                        0.00021175352142945635
                    ],
                    [
                        0.00025320161451066375,
                        0.00024441152427309357
                    ],
                    [
                        0.0002884945440092499,
                        0.0002589347150408787
                    ],
                    [
                        0.0003112048006216888,
                        0.0002439139795776345
                    ],
                    [
                        0.00034594003169776105,
                        0.0002811515969410706
                    ],
                    [
                        0.00032563753024054796,
                        0.00023870869078180783
                    ],
                    [
                        0.0003136516366789508,
                        0.0002470894842683356
                    ],
                    [
                        0.00028696788225254685,
                        0.00020677357011171057
                    ],
                    [
                        0.000285309655574991,
                        0.00020593475704241347
                    ],
                    [
                        0.00024412197050841092,
                        0.00018847920188578546
                    ],
                    [
                        0.00021272615699076324,
                        0.0001959256576039659
                    ],
                    [
                        0.00020647841940133979,
                        0.00015373050576489398
                    ],
                    [
                        0.00023294273294273296,
                        0.00018749515913002245
                    ],
                    [
                        0.0001463007426914173,
                        0.0001370552728432145
                    ],
                    [
                        0.00017962968169620404,
                        0.00017489397053036595
                    ],
                    [
                        0.00020847488384066442,
                        0.00011647299514527053
                    ],
                    [
                        0.00021060945109911808,
                        7.897334649555774e-05
                    ],
                    [
                        0.00015822893663275064,
                        0.00021137616192445108
                    ],
                    [
                        0.0001266354058122033,
                        0.00012287498554411935
                    ],
                    [
                        0.00025411895386824064,
                        6.808492809184134e-05
                    ],
                    [
                        0.00012242535763043867,
                        9.9951875023137e-05
                    ]
                ],
                [
                    [
                        5.1678184876047375e-05,
                        5.7974499470913235e-05
                    ],
                    [
                        5.1678184876047375e-05,
                        5.7974499470913235e-05
                    ],
                    [
                        5.1678184876047375e-05,
                        5.7974499470913235e-05
                    ],
                    [
                        5.1678184876047375e-05,
                        5.7974499470913235e-05
                    ],
                    [
                        5.1678184876047375e-05,
                        5.7974499470913235e-05
                    ],
                    [
                        5.1678184876047375e-05,
                        5.7974499470913235e-05
                    ],
                    [
                        5.1678184876047375e-05,
                        5.7974499470913235e-05
                    ],
                    [
                        5.1678184876047375e-05,
                        5.7974499470913235e-05
                    ],
                    [
                        5.1678184876047375e-05,
                        5.7974499470913235e-05
                    ],
                    [
                        5.1678184876047375e-05,
                        5.7974499470913235e-05
                    ],
                    [
                        5.1678184876047375e-05,
                        5.7974499470913235e-05
                    ],
                    [
                        5.1678184876047375e-05,
                        5.7974499470913235e-05
                    ],
                    [
                        5.1678184876047375e-05,
                        5.7974499470913235e-05
                    ],
                    [
                        5.1678184876047375e-05,
                        5.7974499470913235e-05
                    ],
                    [
                        5.1678184876047375e-05,
                        5.7974499470913235e-05
                    ],
                    [
                        5.1678184876047375e-05,
                        5.7974499470913235e-05
                    ],
                    [
                        5.1678184876047375e-05,
                        5.7974499470913235e-05
                    ],
                    [
                        5.1678184876047375e-05,
                        9.201211348737026e-05
                    ],
                    [
                        5.1678184876047375e-05,
                        7.900814391637292e-05
                    ],
                    [
                        6.541917645897107e-05,
                        5.7974499470913235e-05
                    ],
                    [
                        5.252307063129162e-05,
                        7.503483760317291e-05
                    ],
                    [
                        5.1678184876047375e-05,
                        0.00010833423611863433
                    ],
                    [
                        7.418328257908467e-05,
                        7.483993608669459e-05
                    ],
                    [
                        6.148154484410419e-05,
                        8.84813384813385e-05
                    ],
                    [
                        6.069160197600565e-05,
                        5.802742149491375e-05
                    ],
                    [
                        5.206021448808369e-05,
                        5.7974499470913235e-05
                    ],
                    [
                        5.1678184876047375e-05,
                        6.39063529525837e-05
                    ],
                    [
                        5.1678184876047375e-05,
                        5.7974499470913235e-05
                    ],
                    [
                        5.1678184876047375e-05,
                        6.40317860353242e-05
                    ],
                    [
                        5.1678184876047375e-05,
                        8.149102284377383e-05
                    ],
                    [
                        5.5154234878248816e-05,
                        7.314591247015898e-05
                    ],
                    [
                        5.1678184876047375e-05,
                        8.437759623373027e-05
                    ],
                    [
                        5.1678184876047375e-05,
                        7.340067340067341e-05
                    ],
                    [
                        5.1678184876047375e-05,
                        7.574914950005561e-05
                    ]
                ]
            ],
            "Name": "Binom",
            "Version": "v1"
        },
        "Hiseq": {
            "Date": "6/26/2015",
            "MaxMotifLength": 2,
            "MaxTractLength": 40,
            "Model": [
                [
                    [
                        1.2252579386085038e-05,
                        8.537466874458666e-06
                    ],
                    [
                        6.410960599612103e-06,
                        4.44674200605899e-06
                    ],
                    [
                        4.730858687462813e-06,
                        3.275741494168649e-06
                    ],
                    [
                        4.371613954501363e-06,
                        3.0678998149680226e-06
                    ],
                    [
                        5.073483666850898e-06,
                        3.7277387147094387e-06
                    ],
                    [
                        7.337777796712075e-06,
                        5.835013561550362e-06
                    ],
                    [
                        1.2446935103493928e-05,
                        1.0819814353246748e-05
                    ],
                    [
                        2.2657655419200395e-05,
                        2.1157281432593322e-05
                    ],
                    [
                        4.0426700426587914e-05,
                        3.882913201158633e-05
                    ],
                    [
                        6.48426645241118e-05,
                        6.030590165817529e-05
                    ],
                    [
                        8.815080441948453e-05,
                        7.617329689380004e-05
                    ],
                    [
                        0.00010193634576516342,
                        8.206129841725751e-05
                    ],
                    [
                        0.00010559139647492444,
                        8.117731708701115e-05
                    ],
                    [
                        0.00010329222571059393,
                        7.749562364578466e-05
                    ],
                    [
                        9.859463421302284e-05,
                        7.311140772847669e-05
                    ],
                    [
                        9.331155726410856e-05,
                        6.882549532027937e-05
                    ],
                    [
                        8.817065432253912e-05,
                        6.487922607290031e-05
                    ],
                    [
                        8.340950666918534e-05,
                        6.13117579629785e-05
                    ],
                    [
                        7.907367867454607e-05,
                        5.809821289770589e-05
                    ],
                    [
                        7.514143333531287e-05,
                        5.5198194065519957e-05
                    ],
                    [
                        7.157181224226594e-05,
                        5.2571523034616874e-05
                    ],
                    [
                        6.832199151207696e-05,
                        5.018260277089848e-05
                    ],
                    [
                        6.535288950948459e-05,
                        4.800103395485866e-05
                    ],
                    [
                        6.26304633944974e-05,
                        4.600112122077338e-05
                    ],
                    [
                        6.0125529512844444e-05,
                        4.41611478368964e-05
                    ],
                    [
                        5.7813159493269595e-05,
                        4.246268950380827e-05
                    ],
                    [
                        5.567202432188445e-05,
                        4.0890033594642716e-05
                    ],
                    [
                        5.3683804450810335e-05,
                        3.942970556358727e-05
                    ],
                    [
                        5.183269209985131e-05,
                        3.8070086984420826e-05
                    ],
                    [
                        5.010498112456574e-05,
                        3.680110764137101e-05
                    ],
                    [
                        4.8488731457574374e-05,
                        3.561399635221285e-05
                    ],
                    [
                        4.697349453453015e-05,
                        3.4501078193138746e-05
                    ],
                    [
                        4.55500878646653e-05,
                        3.345560847445306e-05
                    ],
                    [
                        4.4210409068989875e-05,
                        3.247163596975522e-05
                    ],
                    [
                        4.2947281671645854e-05,
                        3.1543889576157724e-05
                    ],
                    [
                        4.175432654074385e-05,
                        3.066768385773244e-05
                    ],
                    [
                        4.06258541558735e-05,
                        2.9838839903706393e-05
                    ],
                    [
                        3.9556773877569285e-05,
                        2.9053618681662563e-05
                    ],
                    [
                        3.854251717150259e-05,
                        2.830866464476056e-05
                    ],
                    [
                        3.75789723475739e-05,
                        2.760095779552607e-05
                    ]
                ],
                [
                    [
                        1.2252579386085038e-05,
                        8.537466874458666e-06
                    ],
                    [
                        6.410960599612103e-06,
                        4.44674200605899e-06
                    ],
                    [
                        4.730858687462813e-06,
                        3.275741494168649e-06
                    ],
                    [
                        4.371613954501363e-06,
                        3.0678998149680226e-06
                    ],
                    [
                        5.073483666850898e-06,
                        3.7277387147094387e-06
                    ],
                    [
                        7.337777796712075e-06,
                        5.835013561550362e-06
                    ],
                    [
                        1.2446935103493928e-05,
                        1.0819814353246748e-05
                    ],
                    [
                        2.2657655419200395e-05,
                        2.1157281432593322e-05
                    ],
                    [
                        4.0426700426587914e-05,
                        3.882913201158633e-05
                    ],
                    [
                        6.48426645241118e-05,
                        6.030590165817529e-05
                    ],
                    [
                        8.815080441948453e-05,
                        7.617329689380004e-05
                    ],
                    [
                        0.00010193634576516342,
                        8.206129841725751e-05
                    ],
                    [
                        0.00010559139647492444,
                        8.117731708701115e-05
                    ],
                    [
                        0.00010329222571059393,
                        7.749562364578466e-05
                    ],
                    [
                        9.859463421302284e-05,
                        7.311140772847669e-05
                    ],
                    [
                        9.331155726410856e-05,
                        6.882549532027937e-05
                    ],
                    [
                        8.817065432253912e-05,
                        6.487922607290031e-05
                    ],
                    [
                        8.340950666918534e-05,
                        6.13117579629785e-05
                    ],
                    [
                        7.907367867454607e-05,
                        5.809821289770589e-05
                    ],
                    [
                        7.514143333531287e-05,
                        5.5198194065519957e-05
                    ],
                    [
                        7.157181224226594e-05,
                        5.2571523034616874e-05
                    ],
                    [
                        6.832199151207696e-05,
                        5.018260277089848e-05
                    ],
                    [
                        6.535288950948459e-05,
                        4.800103395485866e-05
                    ],
                    [
                        6.26304633944974e-05,
                        4.600112122077338e-05
                    ],
                    [
                        6.0125529512844444e-05,
                        4.41611478368964e-05
                    ],
                    [
                        5.7813159493269595e-05,
                        4.246268950380827e-05
                    ],
                    [
                        5.567202432188445e-05,
                        4.0890033594642716e-05
                    ],
                    [
                        5.3683804450810335e-05,
                        3.942970556358727e-05
                    ],
                    [
                        5.183269209985131e-05,
                        3.8070086984420826e-05
                    ],
                    [
                        5.010498112456574e-05,
                        3.680110764137101e-05
                    ],
                    [
                        4.8488731457574374e-05,
                        3.561399635221285e-05
                    ],
                    [
                        4.697349453453015e-05,
                        3.4501078193138746e-05
                    ],
                    [
                        4.55500878646653e-05,
                        3.345560847445306e-05
                    ],
                    [
                        4.4210409068989875e-05,
                        3.247163596975522e-05
                    ],
                    [
                        4.2947281671645854e-05,
                        3.1543889576157724e-05
                    ],
                    [
                        4.175432654074385e-05,
                        3.066768385773244e-05
                    ],
                    [
                        4.06258541558735e-05,
                        2.9838839903706393e-05
                    ],
                    [
                        3.9556773877569285e-05,
                        2.9053618681662563e-05
                    ],
                    [
                        3.854251717150259e-05,
                        2.830866464476056e-05
                    ],
                    [
                        3.75789723475739e-05,
                        2.760095779552607e-05
                    ]
                ]
            ],
            "Name": "Hiseq",
            "Version": "v1"
        },
        "HiseqPCR": {
            "Date": "6/26/2015",
            "MaxMotifLength": 2,
            "MaxTractLength": 40,
            "Model": [
                [
                    [
                        1.2252579386085038e-05,
                        8.537466874458666e-06
                    ],
                    [
                        6.410960599612103e-06,
                        4.44674200605899e-06
                    ],
                    [
                        4.730858687462813e-06,
                        3.275741494168649e-06
                    ],
                    [
                        4.371613954501363e-06,
                        3.0678998149680226e-06
                    ],
                    [
                        5.073483666850898e-06,
                        3.7277387147094387e-06
                    ],
                    [
                        7.337777796712075e-06,
                        5.835013561550362e-06
                    ],
                    [
                        1.2446935103493928e-05,
                        1.0819814353246748e-05
                    ],
                    [
                        2.2657655419200395e-05,
                        2.1157281432593322e-05
                    ],
                    [
                        4.0426700426587914e-05,
                        3.882913201158633e-05
                    ],
                    [
                        6.48426645241118e-05,
                        6.030590165817529e-05
                    ],
                    [
                        8.815080441948453e-05,
                        7.617329689380004e-05
                    ],
                    [
                        0.00010193634576516342,
                        8.206129841725751e-05
                    ],
                    [
                        0.00010559139647492444,
                        8.117731708701115e-05
                    ],
                    [
                        0.00010329222571059393,
                        7.749562364578466e-05
                    ],
                    [
                        9.859463421302284e-05,
                        7.311140772847669e-05
                    ],
                    [
                        9.331155726410856e-05,
                        6.882549532027937e-05
                    ],
                    [
                        8.817065432253912e-05,
                        6.487922607290031e-05
                    ],
                    [
                        8.340950666918534e-05,
                        6.13117579629785e-05
                    ],
                    [
                        7.907367867454607e-05,
                        5.809821289770589e-05
                    ],
                    [
                        7.514143333531287e-05,
                        5.5198194065519957e-05
                    ],
                    [
                        7.157181224226594e-05,
                        5.2571523034616874e-05
                    ],
                    [
                        6.832199151207696e-05,
                        5.018260277089848e-05
                    ],
                    [
                        6.535288950948459e-05,
                        4.800103395485866e-05
                    ],
                    [
                        6.26304633944974e-05,
                        4.600112122077338e-05
                    ],
                    [
                        6.0125529512844444e-05,
                        4.41611478368964e-05
                    ],
                    [
                        5.7813159493269595e-05,
                        4.246268950380827e-05
                    ],
                    [
                        5.567202432188445e-05,
                        4.0890033594642716e-05
                    ],
                    [
                        5.3683804450810335e-05,
                        3.942970556358727e-05
                    ],
                    [
                        5.183269209985131e-05,
                        3.8070086984420826e-05
                    ],
                    [
                        5.010498112456574e-05,
                        3.680110764137101e-05
                    ],
                    [
                        4.8488731457574374e-05,
                        3.561399635221285e-05
                    ],
                    [
                        4.697349453453015e-05,
                        3.4501078193138746e-05
                    ],
                    [
                        4.55500878646653e-05,
                        3.345560847445306e-05
                    ],
                    [
                        4.4210409068989875e-05,
                        3.247163596975522e-05
                    ],
                    [
                        4.2947281671645854e-05,
                        3.1543889576157724e-05
                    ],
                    [
                        4.175432654074385e-05,
                        3.066768385773244e-05
                    ],
                    [
                        4.06258541558735e-05,
                        2.9838839903706393e-05
                    ],
                    [
                        3.9556773877569285e-05,
                        2.9053618681662563e-05
                    ],
                    [
                        3.854251717150259e-05,
                        2.830866464476056e-05
                    ],
                    [
                        3.75789723475739e-05,
                        2.760095779552607e-05
                    ]
                ],
                [
                    [
                        1.2252579386085038e-05,
                        8.537466874458666e-06
                    ],
                    [
                        6.410960599612103e-06,
                        4.44674200605899e-06
                    ],
                    [
                        4.730858687462813e-06,
                        3.275741494168649e-06
                    ],
                    [
                        4.371613954501363e-06,
                        3.0678998149680226e-06
                    ],
                    [
                        5.073483666850898e-06,
                        3.7277387147094387e-06
                    ],
                    [
                        7.337777796712075e-06,
                        5.835013561550362e-06
                    ],
                    [
                        1.2446935103493928e-05,
                        1.0819814353246748e-05
                    ],
                    [
                        2.2657655419200395e-05,
                        2.1157281432593322e-05
                    ],
                    [
                        4.0426700426587914e-05,
                        3.882913201158633e-05
                    ],
                    [
                        6.48426645241118e-05,
                        6.030590165817529e-05
                    ],
                    [
                        8.815080441948453e-05,
                        7.617329689380004e-05
                    ],
                    [
                        0.00010193634576516342,
                        8.206129841725751e-05
                    ],
                    [
                        0.00010559139647492444,
                        8.117731708701115e-05
                    ],
                    [
                        0.00010329222571059393,
                        7.749562364578466e-05
                    ],
                    [
                        9.859463421302284e-05,
                        7.311140772847669e-05
                    ],
                    [
                        9.331155726410856e-05,
                        6.882549532027937e-05
                    ],
                    [
                        8.817065432253912e-05,
                        6.487922607290031e-05
                    ],
                    [
                        8.340950666918534e-05,
                        6.13117579629785e-05
                    ],
                    [
                        7.907367867454607e-05,
                        5.809821289770589e-05
                    ],
                    [
                        7.514143333531287e-05,
                        5.5198194065519957e-05
                    ],
                    [
                        7.157181224226594e-05,
                        5.2571523034616874e-05
                    ],
                    [
                        6.832199151207696e-05,
                        5.018260277089848e-05
                    ],
                    [
                        6.535288950948459e-05,
                        4.800103395485866e-05
                    ],
                    [
                        6.26304633944974e-05,
                        4.600112122077338e-05
                    ],
                    [
                        6.0125529512844444e-05,
                        4.41611478368964e-05
                    ],
                    [
                        5.7813159493269595e-05,
                        4.246268950380827e-05
                    ],
                    [
                        5.567202432188445e-05,
                        4.0890033594642716e-05
                    ],
                    [
                        5.3683804450810335e-05,
                        3.942970556358727e-05
                    ],
                    [
                        5.183269209985131e-05,
                        3.8070086984420826e-05
                    ],
                    [
                        5.010498112456574e-05,
                        3.680110764137101e-05
                    ],
                    [
                        4.8488731457574374e-05,
                        3.561399635221285e-05
                    ],
                    [
                        4.697349453453015e-05,
                        3.4501078193138746e-05
                    ],
                    [
                        4.55500878646653e-05,
                        3.345560847445306e-05
                    ],
                    [
                        4.4210409068989875e-05,
                        3.247163596975522e-05
                    ],
                    [
                        4.2947281671645854e-05,
                        3.1543889576157724e-05
                    ],
                    [
                        4.175432654074385e-05,
                        3.066768385773244e-05
                    ],
                    [
                        4.06258541558735e-05,
                        2.9838839903706393e-05
                    ],
                    [
                        3.9556773877569285e-05,
                        2.9053618681662563e-05
                    ],
                    [
                        3.854251717150259e-05,
                        2.830866464476056e-05
                    ],
                    [
                        3.75789723475739e-05,
                        2.760095779552607e-05
                    ]
                ]
            ],
            "Name": "HiseqPCR",
            "Version": "v1"
        },
        "NextSeq": {
            "Date": "6/26/2015",
            "MaxMotifLength": 2,
            "MaxTractLength": 40,
            "Model": [
                [
                    [
                        1.2252579386085038e-05,
                        8.537466874458666e-06
                    ],
                    [
                        6.410960599612103e-06,
                        4.44674200605899e-06
                    ],
                    [
                        4.730858687462813e-06,
                        3.275741494168649e-06
                    ],
                    [
                        4.371613954501363e-06,
                        3.0678998149680226e-06
                    ],
                    [
                        5.073483666850898e-06,
                        3.7277387147094387e-06
                    ],
                    [
                        7.337777796712075e-06,
                        5.835013561550362e-06
                    ],
                    [
                        1.2446935103493928e-05,
                        1.0819814353246748e-05
                    ],
                    [
                        2.2657655419200395e-05,
                        2.1157281432593322e-05
                    ],
                    [
                        4.0426700426587914e-05,
                        3.882913201158633e-05
                    ],
                    [
                        6.48426645241118e-05,
                        6.030590165817529e-05
                    ],
                    [
                        8.815080441948453e-05,
                        7.617329689380004e-05
                    ],
                    [
                        0.00010193634576516342,
                        8.206129841725751e-05
                    ],
                    [
                        0.00010559139647492444,
                        8.117731708701115e-05
                    ],
                    [
                        0.00010329222571059393,
                        7.749562364578466e-05
                    ],
                    [
                        9.859463421302284e-05,
                        7.311140772847669e-05
                    ],
                    [
                        9.331155726410856e-05,
                        6.882549532027937e-05
                    ],
                    [
                        8.817065432253912e-05,
                        6.487922607290031e-05
                    ],
                    [
                        8.340950666918534e-05,
                        6.13117579629785e-05
                    ],
                    [
                        7.907367867454607e-05,
                        5.809821289770589e-05
                    ],
                    [
                        7.514143333531287e-05,
                        5.5198194065519957e-05
                    ],
                    [
                        7.157181224226594e-05,
                        5.2571523034616874e-05
                    ],
                    [
                        6.832199151207696e-05,
                        5.018260277089848e-05
                    ],
                    [
                        6.535288950948459e-05,
                        4.800103395485866e-05
                    ],
                    [
                        6.26304633944974e-05,
                        4.600112122077338e-05
                    ],
                    [
                        6.0125529512844444e-05,
                        4.41611478368964e-05
                    ],
                    [
                        5.7813159493269595e-05,
                        4.246268950380827e-05
                    ],
                    [
                        5.567202432188445e-05,
                        4.0890033594642716e-05
                    ],
                    [
                        5.3683804450810335e-05,
                        3.942970556358727e-05
                    ],
                    [
                        5.183269209985131e-05,
                        3.8070086984420826e-05
                    ],
                    [
                        5.010498112456574e-05,
                        3.680110764137101e-05
                    ],
                    [
                        4.8488731457574374e-05,
                        3.561399635221285e-05
                    ],
                    [
                        4.697349453453015e-05,
                        3.4501078193138746e-05
                    ],
                    [
                        4.55500878646653e-05,
                        3.345560847445306e-05
                    ],
                    [
                        4.4210409068989875e-05,
                        3.247163596975522e-05
                    ],
                    [
                        4.2947281671645854e-05,
                        3.1543889576157724e-05
                    ],
                    [
                        4.175432654074385e-05,
                        3.066768385773244e-05
                    ],
                    [
                        4.06258541558735e-05,
                        2.9838839903706393e-05
                    ],
                    [
                        3.9556773877569285e-05,
                        2.9053618681662563e-05
                    ],
                    [
                        3.854251717150259e-05,
                        2.830866464476056e-05
                    ],
                    [
                        3.75789723475739e-05,
                        2.760095779552607e-05
                    ]
                ],
                [
                    [
                        1.2252579386085038e-05,
                        8.537466874458666e-06
                    ],
                    [
                        6.410960599612103e-06,
                        4.44674200605899e-06
                    ],
                    [
                        4.730858687462813e-06,
                        3.275741494168649e-06
                    ],
                    [
                        4.371613954501363e-06,
                        3.0678998149680226e-06
                    ],
                    [
                        5.073483666850898e-06,
                        3.7277387147094387e-06
                    ],
                    [
                        7.337777796712075e-06,
                        5.835013561550362e-06
                    ],
                    [
                        1.2446935103493928e-05,
                        1.0819814353246748e-05
                    ],
                    [
                        2.2657655419200395e-05,
                        2.1157281432593322e-05
                    ],
                    [
                        4.0426700426587914e-05,
                        3.882913201158633e-05
                    ],
                    [
                        6.48426645241118e-05,
                        6.030590165817529e-05
                    ],
                    [
                        8.815080441948453e-05,
                        7.617329689380004e-05
                    ],
                    [
                        0.00010193634576516342,
                        8.206129841725751e-05
                    ],
                    [
                        0.00010559139647492444,
                        8.117731708701115e-05
                    ],
                    [
                        0.00010329222571059393,
                        7.749562364578466e-05
                    ],
                    [
                        9.859463421302284e-05,
                        7.311140772847669e-05
                    ],
                    [
                        9.331155726410856e-05,
                        6.882549532027937e-05
                    ],
                    [
                        8.817065432253912e-05,
                        6.487922607290031e-05
                    ],
                    [
                        8.340950666918534e-05,
                        6.13117579629785e-05
                    ],
                    [
                        7.907367867454607e-05,
                        5.809821289770589e-05
                    ],
                    [
                        7.514143333531287e-05,
                        5.5198194065519957e-05
                    ],
                    [
                        7.157181224226594e-05,
                        5.2571523034616874e-05
                    ],
                    [
                        6.832199151207696e-05,
                        5.018260277089848e-05
                    ],
                    [
                        6.535288950948459e-05,
                        4.800103395485866e-05
                    ],
                    [
                        6.26304633944974e-05,
                        4.600112122077338e-05
                    ],
                    [
                        6.0125529512844444e-05,
                        4.41611478368964e-05
                    ],
                    [
                        5.7813159493269595e-05,
                        4.246268950380827e-05
                    ],
                    [
                        5.567202432188445e-05,
                        4.0890033594642716e-05
                    ],
                    [
                        5.3683804450810335e-05,
                        3.942970556358727e-05
                    ],
                    [
                        5.183269209985131e-05,
                        3.8070086984420826e-05
                    ],
                    [
                        5.010498112456574e-05,
                        3.680110764137101e-05
                    ],
                    [
                        4.8488731457574374e-05,
                        3.561399635221285e-05
                    ],
                    [
                        4.697349453453015e-05,
                        3.4501078193138746e-05
                    ],
                    [
                        4.55500878646653e-05,
                        3.345560847445306e-05
                    ],
                    [
                        4.4210409068989875e-05,
                        3.247163596975522e-05
                    ],
                    [
                        4.2947281671645854e-05,
                        3.1543889576157724e-05
                    ],
                    [
                        4.175432654074385e-05,
                        3.066768385773244e-05
                    ],
                    [
                        4.06258541558735e-05,
                        2.9838839903706393e-05
                    ],
                    [
                        3.9556773877569285e-05,
                        2.9053618681662563e-05
                    ],
                    [
                        3.854251717150259e-05,
                        2.830866464476056e-05
                    ],
                    [
                        3.75789723475739e-05,
                        2.760095779552607e-05
                    ]
                ]
            ],
            "Name": "NextSeq",
            "Version": "v1"
        },
        "Xten": {
            "Date": "6/26/2015",
            "MaxMotifLength": 2,
            "MaxTractLength": 40,
            "Model": [
                [
                    [
                        1.2252579386085038e-05,
                        8.537466874458666e-06
                    ],
                    [
                        6.410960599612103e-06,
                        4.44674200605899e-06
                    ],
                    [
                        4.730858687462813e-06,
                        3.275741494168649e-06
                    ],
                    [
                        4.371613954501363e-06,
                        3.0678998149680226e-06
                    ],
                    [
                        5.073483666850898e-06,
                        3.7277387147094387e-06
                    ],
                    [
                        7.337777796712075e-06,
                        5.835013561550362e-06
                    ],
                    [
                        1.2446935103493928e-05,
                        1.0819814353246748e-05
                    ],
                    [
                        2.2657655419200395e-05,
                        2.1157281432593322e-05
                    ],
                    [
                        4.0426700426587914e-05,
                        3.882913201158633e-05
                    ],
                    [
                        6.48426645241118e-05,
                        6.030590165817529e-05
                    ],
                    [
                        8.815080441948453e-05,
                        7.617329689380004e-05
                    ],
                    [
                        0.00010193634576516342,
                        8.206129841725751e-05
                    ],
                    [
                        0.00010559139647492444,
                        8.117731708701115e-05
                    ],
                    [
                        0.00010329222571059393,
                        7.749562364578466e-05
                    ],
                    [
                        9.859463421302284e-05,
                        7.311140772847669e-05
                    ],
                    [
                        9.331155726410856e-05,
                        6.882549532027937e-05
                    ],
                    [
                        8.817065432253912e-05,
                        6.487922607290031e-05
                    ],
                    [
                        8.340950666918534e-05,
                        6.13117579629785e-05
                    ],
                    [
                        7.907367867454607e-05,
                        5.809821289770589e-05
                    ],
                    [
                        7.514143333531287e-05,
                        5.5198194065519957e-05
                    ],
                    [
                        7.157181224226594e-05,
                        5.2571523034616874e-05
                    ],
                    [
                        6.832199151207696e-05,
                        5.018260277089848e-05
                    ],
                    [
                        6.535288950948459e-05,
                        4.800103395485866e-05
                    ],
                    [
                        6.26304633944974e-05,
                        4.600112122077338e-05
                    ],
                    [
                        6.0125529512844444e-05,
                        4.41611478368964e-05
                    ],
                    [
                        5.7813159493269595e-05,
                        4.246268950380827e-05
                    ],
                    [
                        5.567202432188445e-05,
                        4.0890033594642716e-05
                    ],
                    [
                        5.3683804450810335e-05,
                        3.942970556358727e-05
                    ],
                    [
                        5.183269209985131e-05,
                        3.8070086984420826e-05
                    ],
                    [
                        5.010498112456574e-05,
                        3.680110764137101e-05
                    ],
                    [
                        4.8488731457574374e-05,
                        3.561399635221285e-05
                    ],
                    [
                        4.697349453453015e-05,
                        3.4501078193138746e-05
                    ],
                    [
                        4.55500878646653e-05,
                        3.345560847445306e-05
                    ],
                    [
                        4.4210409068989875e-05,
                        3.247163596975522e-05
                    ],
                    [
                        4.2947281671645854e-05,
                        3.1543889576157724e-05
                    ],
                    [
                        4.175432654074385e-05,
                        3.066768385773244e-05
                    ],
                    [
                        4.06258541558735e-05,
                        2.9838839903706393e-05
                    ],
                    [
                        3.9556773877569285e-05,
                        2.9053618681662563e-05
                    ],
                    [
                        3.854251717150259e-05,
                        2.830866464476056e-05
                    ],
                    [
                        3.75789723475739e-05,
                        2.760095779552607e-05
                    ]
                ],
                [
                    [
                        1.2252579386085038e-05,
                        8.537466874458666e-06
                    ],
                    [
                        6.410960599612103e-06,
                        4.44674200605899e-06
                    ],
                    [
                        4.730858687462813e-06,
                        3.275741494168649e-06
                    ],
                    [
                        4.371613954501363e-06,
                        3.0678998149680226e-06
                    ],
                    [
                        5.073483666850898e-06,
                        3.7277387147094387e-06
                    ],
                    [
                        7.337777796712075e-06,
                        5.835013561550362e-06
                    ],
                    [
                        1.2446935103493928e-05,
                        1.0819814353246748e-05
                    ],
                    [
                        2.2657655419200395e-05,
                        2.1157281432593322e-05
                    ],
                    [
                        4.0426700426587914e-05,
                        3.882913201158633e-05
                    ],
                    [
                        6.48426645241118e-05,
                        6.030590165817529e-05
                    ],
                    [
                        8.815080441948453e-05,
                        7.617329689380004e-05
                    ],
                    [
                        0.00010193634576516342,
                        8.206129841725751e-05
                    ],
                    [
                        0.00010559139647492444,
                        8.117731708701115e-05
                    ],
                    [
                        0.00010329222571059393,
                        7.749562364578466e-05
                    ],
                    [
                        9.859463421302284e-05,
                        7.311140772847669e-05
                    ],
                    [
                        9.331155726410856e-05,
                        6.882549532027937e-05
                    ],
                    [
                        8.817065432253912e-05,
                        6.487922607290031e-05
                    ],
                    [
                        8.340950666918534e-05,
                        6.13117579629785e-05
                    ],
                    [
                        7.907367867454607e-05,
                        5.809821289770589e-05
                    ],
                    [
                        7.514143333531287e-05,
                        5.5198194065519957e-05
                    ],
                    [
                        7.157181224226594e-05,
                        5.2571523034616874e-05
                    ],
                    [
                        6.832199151207696e-05,
                        5.018260277089848e-05
                    ],
                    [
                        6.535288950948459e-05,
                        4.800103395485866e-05
                    ],
                    [
                        6.26304633944974e-05,
                        4.600112122077338e-05
                    ],
                    [
                        6.0125529512844444e-05,
                        4.41611478368964e-05
                    ],
                    [
                        5.7813159493269595e-05,
                        4.246268950380827e-05
                    ],
                    [
                        5.567202432188445e-05,
                        4.0890033594642716e-05
                    ],
                    [
                        5.3683804450810335e-05,
                        3.942970556358727e-05
                    ],
                    [
                        5.183269209985131e-05,
                        3.8070086984420826e-05
                    ],
                    [
                        5.010498112456574e-05,
                        3.680110764137101e-05
                    ],
                    [
                        4.8488731457574374e-05,
                        3.561399635221285e-05
                    ],
                    [
                        4.697349453453015e-05,
                        3.4501078193138746e-05
                    ],
                    [
                        4.55500878646653e-05,
                        3.345560847445306e-05
                    ],
                    [
                        4.4210409068989875e-05,
                        3.247163596975522e-05
                    ],
                    [
                        4.2947281671645854e-05,
                        3.1543889576157724e-05
                    ],
                    [
                        4.175432654074385e-05,
                        3.066768385773244e-05
                    ],
                    [
                        4.06258541558735e-05,
                        2.9838839903706393e-05
                    ],
                    [
                        3.9556773877569285e-05,
                        2.9053618681662563e-05
                    ],
                    [
                        3.854251717150259e-05,
                        2.830866464476056e-05
                    ],
                    [
                        3.75789723475739e-05,
                        2.760095779552607e-05
                    ]
                ]
            ],
            "Name": "Xten",
            "Version": "v1"
        }
    }
}
